Workbook

Sheet Fahrplan
A1: FAHRPLAN: VOM START BIS ZUM BOOM
A2: Gelbe Felder ausfüllen: Spalte F (Ja/Nein) und G (Datum). Kosten sind Schätzungen (Gewerbe 20–60 €, Etsy 0,20 $ pro Angebot, Werbung frei wählbar).
A3: Fortschritt: | C3: =COUNTIF(F6:F27,"Ja")&" von "&COUNTA(C6:C27)&" Schritten erledigt" -> 0 von 22 Schritten erledigt | E3: =SUM(E6:E27) -> 76 | F3: =COUNTIF(F6:F27,"Ja")/COUNTA(C6:C27) -> 0
A5: Phase | B5: Zeitraum | C5: Schritt | D5: Details | E5: Kosten (€) | F5: Erledigt | G5: Datum
A6: 0 Grundlage | B6: Woche 1 | C6: Gewerbe anmelden | D6: online beim Gewerbeamt, Kleinunternehmer ankreuzen | E6: 40 | F6: Nein
A7: 0 Grundlage | B7: Woche 1 | C7: Steuernummer beantragen | D7: Fragebogen zur steuerlichen Erfassung über ELSTER | E7: 0 | F7: Nein
A8: 0 Grundlage | B8: Woche 1 | C8: Etsy-Shop eröffnen | D8: Ausweis, IBAN, Kreditkarte; Impressum eintragen | E8: 0 | F8: Nein
A9: 0 Grundlage | B9: Woche 1 | C9: Higgsfield-Lizenz prüfen | D9: erlaubt dein Tarif die kommerzielle Nutzung der Fotos? | E9: 0 | F9: Nein
A10: 1 Start | B10: Woche 1–2 | C10: 29 Angebote auf Etsy einstellen | D10: Bilder, Texte (ETSY-TEXTE.md) und ZIPs sind fertig | E10: 6 | F10: Nein
A11: 1 Start | B11: Woche 1–2 | C11: Widerruf für Downloads aktivieren | D11: Etsy-Einstellungen > digitale Artikel | E11: 0 | F11: Nein
A12: 1 Start | B12: Woche 1–2 | C12: Nachricht nach dem Kauf eintragen | D12: Text steht in ETSY-TEXTE.md | E12: 0 | F12: Nein
A13: 1 Start | B13: Woche 1–2 | C13: Pinterest-Unternehmenskonto anlegen | D13: 4–5 Pinnwände, Pins verlinken auf Etsy | E13: 0 | F13: Nein
A14: 1 Start | B14: Woche 1–2 | C14: 2–3 Pins pro Tag posten | D14: Texte in 00_Pin-Texte.md | E14: 0 | F14: Nein
A15: 2 Erster Euro | B15: Woche 2–8 | C15: Start-Rabatt 30 % für 2 Wochen | D15: Etsy > Marketing > Sonderangebote | E15: 0 | F15: Nein
A16: 2 Erster Euro | B16: Woche 2–8 | C16: Etsy-Werbung testen | D16: 1–2 € pro Tag für 2–3 Wochen | E16: 30 | F16: Nein
A17: 2 Erster Euro | B17: Woche 2–8 | C17: Bewertungen sammeln | D17: nur über die Nachricht nach dem Kauf, nichts kaufen oder fälschen | E17: 0 | F17: Nein
... A27: 4 Wachsen | B27: Monat 4–12 | C27: Kurze Videos ohne Gesicht | D27: Vorlagen zeigen auf TikTok und Instagram | E27: 0 | F27: Nein

Sheet Gewinn
A1: GEWINN-KALKULATION
A2: Gelbe Felder kannst du ändern, alles andere rechnet sich selbst. Die Verkaufszahlen sind Annahmen, keine Prognose. Keine Steuerberatung.
A4: ANNAHMEN
A5: Durchschnittlicher Preis pro Verkauf | B5: 14
A6: Etsy Transaktionsgebühr | B6: 0.065
A7: Etsy Zahlungsgebühr (%) | B7: 0.04
A8: Etsy Zahlungsgebühr (fix) | B8: 0.3
A9: Neu-Einstellgebühr pro Verkauf | B9: 0.18
A10: MwSt. auf Etsy-Gebühren | B10: 0.19
A11: Einmalkosten Start (Gewerbe + 29 Angebote) | B11: 46
A12: Feste Kosten pro Monat (z. B. Apps, Abo) | B12: 0
A13: Ziel-Gewinn pro Monat | B13: 500
A15: Gebühren pro Verkauf | B15: =(B5*(B6+B7)+B8+B9)*(1+B10) -> 2.3205
A16: Bleibt pro Verkauf | B16: =B5-B15 -> 11.6795
A17: Das sind vom Preis | B17: =IF(B5=0,0,B16/B5) -> 0.83425
A19: ZIELRECHNER
A20: Verkäufe pro Monat für dein Ziel | B20: =IF(B16<=0,"-",ROUNDUP((B13+B12)/B16,0)) -> 43
A21: … das sind pro Tag etwa | B21: =IF(B16<=0,"-",ROUND(B20/30,1)) -> 1.4
A22: Bei 2 % Kaufrate brauchst du Aufrufe im Monat | B22: =IF(B16<=0,"-",ROUNDUP(B20/0.02,0)) -> 2150
A24: DIE ERSTEN 12 MONATE IN 3 SZENARIEN
A25: Monat | B25: Werbung (€) | C25: Verkäufe vorsichtig | D25: Verkäufe realistisch | E25: Verkäufe gut | F25: Gewinn vorsichtig | G25: Gewinn realistisch | H25: Gewinn gut | I25: Summe vorsichtig | J25: Summe realistisch | K25: Summe gut
A26: 1 | B26: 30 | C26: 0 | D26: 1 | E26: 2 | F26: =C26*$B$16-$B26-$B$12-$B$11 -> -76 | G26: =D26*$B$16-$B26-$B$12-$B$11 -> -64.3205 | H26: =E26*$B$16-$B26-$B$12-$B$11 -> -52.641 | I26: =SUM(F$26:F26) -> -76 | J26: =SUM(G$26:G26) -> -64.3205 | K26: =SUM(H$26:H26) -> -52.641
A27: 2 | B27: 30 | C27: 1 | D27: 3 | E27: 6 | F27: =C27*$B$16-$B27-$B$12 -> -18.3205 | G27: =D27*$B$16-$B27-$B$12 -> 5.0385 | H27: =E27*$B$16-$B27-$B$12 -> 40.077 | I27: =SUM(F$26:F27) -> -94.3205 | J27: =SUM(G$26:G27) -> -59.282 | K27: =SUM(H$26:H27) -> -12.564
A28: 3 | B28: 15 | C28: 2 | D28: 6 | E28: 12 | F28: =C28*$B$16-$B28-$B$12 -> 8.359 | G28: =D28*$B$16-$B28-$B$12 -> 55.077 | H28: =E28*$B$16-$B28-$B$12 -> 125.154 | I28: =SUM(F$26:F28) -> -85.9615 | J28: =SUM(G$26:G28) -> -4.205 | K28: =SUM(H$26:H28) -> 112.59
A29: 4 | B29: 15 | C29: 3 | D29: 10 | E29: 20 | F29: =C29*$B$16-$B29-$B$12 -> 20.0385 | G29: =D29*$B$16-$B29-$B$12 -> 101.795 | H29: =E29*$B$16-$B29-$B$12 -> 218.59 | I29: =SUM(F$26:F29) -> -65.923 | J29: =SUM(G$26:G29) -> 97.59 | K29: =SUM(H$26:H29) -> 331.18
A30: 5 | B30: 15 | C30: 4 | D30: 14 | E30: 30 | F30: =C30*$B$16-$B30-$B$12 -> 31.718 | G30: =D30*$B$16-$B30-$B$12 -> 148.513 | H30: =E30*$B$16-$B30-$B$12 -> 335.385 | I30: =SUM(F$26:F30) -> -34.205 | J30: =SUM(G$26:G30) -> 246.103 | K30: =SUM(H$26:H30) -> 666.565
A31: 6 | B31: 15 | C31: 5 | D31: 18 | E31: 40 | F31: =C31*$B$16-$B31-$B$12 -> 43.3975 | G31: =D31*$B$16-$B31-$B$12 -> 195.231 | H31: =E31*$B$16-$B31-$B$12 -> 452.18 | I31: =SUM(F$26:F31) -> 9.1925 | J31: =SUM(G$26:G31) -> 441.334 | K31: =SUM(H$26:H31) -> 1118.745
A32: 7 | B32: 20 | C32: 6 | D32: 24 | E32: 55 | F32: =C32*$B$16-$B32-$B$12 -> 50.077 | G32: =D32*$B$16-$B32-$B$12 -> 260.308 | H32: =E32*$B$16-$B32-$B$12 -> 622.3725 | I32: =SUM(F$26:F32) -> 59.2695 | J32: =SUM(G$26:G32) -> 701.642 | K32: =SUM(H$26:H32) -> 1741.1175
A33: 8 | B33: 20 | C33: 7 | D33: 30 | E33: 70 | F33: =C33*$B$16-$B33-$B$12 -> 61.7565 | G33: =D33*$B$16-$B33-$B$12 -> 330.385 | H33: =E33*$B$16-$B33-$B$12 -> 797.565 | I33: =SUM(F$26:F33) -> 121.026 | J33: =SUM(G$26:G33) -> 1032.027 | K33: =SUM(H$26:H33) -> 2538.6825
A34: 9 | B34: 20 | C34: 8 | D34: 36 | E34: 85 | F34: =C34*$B$16-$B34-$B$12 -> 73.436 | G34: =D34*$B$16-$B34-$B$12 -> 400.462 | H34: =E34*$B$16-$B34-$B$12 -> 972.7575 | I34: =SUM(F$26:F34) -> 194.462 | J34: =SUM(G$26:G34) -> 1432.489 | K34: =SUM(H$26:H34) -> 3511.44
A35: 10 | B35: 20 | C35: 9 | D35: 42 | E35: 100 | F35: =C35*$B$16-$B35-$B$12 -> 85.1155 | G35: =D35*$B$16-$B35-$B$12 -> 470.539 | H35: =E35*$B$16-$B35-$B$12 -> 1147.95 | I35: =SUM(F$26:F35) -> 279.5775 | J35: =SUM(G$26:G35) -> 1903.028 | K35: =SUM(H$26:H35) -> 4659.39
A36: 11 | B36: 30 | C36: 10 | D36: 50 | E36: 120 | F36: =C36*$B$16-$B36-$B$12 -> 86.795 | G36: =D36*$B$16-$B36-$B$12 -> 553.975 | H36: =E36*$B$16-$B36-$B$12 -> 1371.54 | I36: =SUM(F$26:F36) -> 366.3725 | J36: =SUM(G$26:G36) -> 2457.003 | K36: =SUM(H$26:H36) -> 6030.93
A37: 12 | B37: 30 | C37: 12 | D37: 60 | E37: 140 | F37: =C37*$B$16-$B37-$B$12 -> 110.154 | G37: =D37*$B$16-$B37-$B$12 -> 670.77 | H37: =E37*$B$16-$B37-$B$12 -> 1605.13 | I37: =SUM(F$26:F37) -> 476.5265 | J37: =SUM(G$26:G37) -> 3127.773 | K37: =SUM(H$26:H37) -> 7636.06
A38: Jahr | B38: =SUM(B26:B37) -> 260 | C38: =SUM(C26:C37) -> 67 | D38: =SUM(D26:D37) -> 294 | E38: =SUM(E26:E37) -> 680 | F38: =SUM(F26:F37) -> 476.5265 | G38: =SUM(G26:G37) -> 3127.773 | H38: =SUM(H26:H37) -> 7636.06
A40: Ab Monat im Plus | I40: =IFERROR(MATCH(TRUE(),INDEX(I26:I37>0,0),0),"nicht im 1. Jahr") -> 6 | J40: =IFERROR(MATCH(TRUE(),INDEX(J26:J37>0,0),0),"nicht im 1. Jahr") -> 4 | K40: =IFERROR(MATCH(TRUE(),INDEX(K26:K37>0,0),0),"nicht im 1. Jahr") -> 3
A41: Monat 12: Gewinn pro Monat | I41: =F37 -> 110.154 | J41: =G37 -> 670.77 | K41: =H37 -> 1605.13
A43: Die Verkäufe pro Monat sind Annahmen: vorsichtig = kaum Pinterest, realistisch = regelmäßig pinnen und Gewinner ausbauen, gut = englische Versionen und Shopify ab Monat 6. Ändere sie, sobald du echte Zahlen hast (Blatt „Zahlen“).

Sheet Pro Produkt
A1: GEWINN PRO PRODUKT
A2: Gebühren-Annahmen kommen aus dem Blatt „Gewinn“. Preise in Spalte C kannst du ändern.
A4: Nr. | B4: Produkt | C4: Preis | D4: Etsy-Gebühren | E4: Bleibt dir | F4: Anteil
A5: 01 | B5: UGC Starter-Kit auf Deutsch | C5: 14 | D5: =(C5*(Gewinn!$B$6+Gewinn!$B$7)+Gewinn!$B$8+Gewinn!$B$9)*(1+Gewinn!$B$10) -> 2.3205 | E5: =C5-D5 -> 11.6795 | F5: =IF(C5=0,0,E5/C5) -> 0.83425
A6: 02 | B6: Media-Kit Vorlage 1 Seite auf Deutsch | C6: 12 | D6: =(C6*(Gewinn!$B$6+Gewinn!$B$7)+Gewinn!$B$8+Gewinn!$B$9)*(1+Gewinn!$B$10) -> 2.0706 | E6: =C6-D6 -> 9.9294 | F6: =IF(C6=0,0,E6/C6) -> 0.82745
A7: 03 | B7: Preisliste Vorlage für Creator | C7: 10 | D7: =(C7*(Gewinn!$B$6+Gewinn!$B$7)+Gewinn!$B$8+Gewinn!$B$9)*(1+Gewinn!$B$10) -> 1.8207 | E7: =C7-D7 -> 8.1793 | F7: =IF(C7=0,0,E7/C7) -> 0.81793
A8: 04 | B8: Angebot Vorlage für Kooperationen | C8: 10 | D8: =(C8*(Gewinn!$B$6+Gewinn!$B$7)+Gewinn!$B$8+Gewinn!$B$9)*(1+Gewinn!$B$10) -> 1.8207 | E8: =C8-D8 -> 8.1793 | F8: =IF(C8=0,0,E8/C8) -> 0.81793
A9: 05 | B9: Rechnung Vorlage für Creator | C9: 9 | D9: =(C9*(Gewinn!$B$6+Gewinn!$B$7)+Gewinn!$B$8+Gewinn!$B$9)*(1+Gewinn!$B$10) -> 1.69575 | E9: =C9-D9 -> 7.30425 | F9: =IF(C9=0,0,E9/C9) -> 0.81158333
A10: 06 | B10: Briefing Formular Vorlage für UGC Creator | C10: 9 | D10: =(C10*(Gewinn!$B$6+Gewinn!$B$7)+Gewinn!$B$8+Gewinn!$B$9)*(1+Gewinn!$B$10) -> 1.69575 | E10: =C10-D10 -> 7.30425 | F10: =IF(C10=0,0,E10/C10) -> 0.81158333
A11: 07 | B11: UGC Portfolio Vorlage im Querformat | C11: 15 | D11: =(C11*(Gewinn!$B$6+Gewinn!$B$7)+Gewinn!$B$8+Gewinn!$B$9)*(1+Gewinn!$B$10) -> 2.44545 | E11: =C11-D11 -> 12.55455 | F11: =IF(C11=0,0,E11/C11) -> 0.83697
A12: 08 | B12: Link in Bio Vorlage auf Deutsch | C12: 9 | D12: =(C12*(Gewinn!$B$6+Gewinn!$B$7)+Gewinn!$B$8+Gewinn!$B$9)*(1+Gewinn!$B$10) -> 1.69575 | E12: =C12-D12 -> 7.30425 | F12: =IF(C12=0,0,E12/C12) -> 0.81158333
A13: 09 | B13: Case Study Vorlage für UGC Creator | C13: 12 | D13: =(C13*(Gewinn!$B$6+Gewinn!$B$7)+Gewinn!$B$8+Gewinn!$B$9)*(1+Gewinn!$B$10) -> 2.0706 | E13: =C13-D13 -> 9.9294 | F13: =IF(C13=0,0,E13/C13) -> 0.82745
A14: 10 | B14: Content Planer Vorlage auf Deutsch | C14: 10 | D14: =(C14*(Gewinn!$B$6+Gewinn!$B$7)+Gewinn!$B$8+Gewinn!$B$9)*(1+Gewinn!$B$10) -> 1.8207 | E14: =C14-D14 -> 8.1793 | F14: =IF(C14=0,0,E14/C14) -> 0.81793
A15: 11 | B15: 100 Hooks für Videos auf Deutsch | C15: 12 | D15: =(C15*(Gewinn!$B$6+Gewinn!$B$7)+Gewinn!$B$8+Gewinn!$B$9)*(1+Gewinn!$B$10) -> 2.0706 | E15: =C15-D15 -> 9.9294 | F15: =IF(C15=0,0,E15/C15) -> 0.82745
A16: 12 | B16: Skript Vorlage für UGC Videos | C16: 9 | D16: =(C16*(Gewinn!$B$6+Gewinn!$B$7)+Gewinn!$B$8+Gewinn!$B$9)*(1+Gewinn!$B$10) -> 1.69575 | E16: =C16-D16 -> 7.30425 | F16: =IF(C16=0,0,E16/C16) -> 0.81158333
... A31: 27 | B31: Abo Creator Komplettpaket | C31: 35 | D31: =(C31*(Gewinn!$B$6+Gewinn!$B$7)+Gewinn!$B$8+Gewinn!$B$9)*(1+Gewinn!$B$10) -> 4.94445 | E31: =C31-D31 -> 30.05555 | F31: =IF(C31=0,0,E31/C31) -> 0.85873

Sheet Zahlen
A1: MEINE ZAHLEN PRO WOCHE
A2: Gelbe Felder aus der Etsy-Statistik abschreiben. Zeile 5 ist ein Beispiel, gern überschreiben. Gebühren: ca. 6,5 % Transaktion + 4 % Zahlung + 0,30 € pro Verkauf (Etsy Deutschland, Stand 2026, bitte prüfen).
A4: Woche ab | B4: Aufrufe | C4: Favoriten | D4: Verkäufe | E4: Umsatz (€) | F4: Gebühren ca. (€) | G4: Werbung (€) | H4: Gewinn ca. (€) | I4: Kaufrate | K4: Gebühr % | L4: 0.105
A5: 46328 | B5: 120 | C5: 9 | D5: 1 | E5: 12 | F5: =IF(E5="","",E5*$L$4+D5*$L$5) -> 1.56 | G5: 7 | H5: =IF(E5="","",E5-F5-G5) -> 3.44 | I5: =IF(OR(B5="",B5=0),"",D5/B5) -> 0.0083333333 | K5: Gebühr pro Verkauf | L5: 0.3
F6: =IF(E6="","",E6*$L$4+D6*$L$5) | H6: =IF(E6="","",E6-F6-G6) | I6: =IF(OR(B6="",B6=0),"",D6/B6)
F7: =IF(E7="","",E7*$L$4+D7*$L$5) | H7: =IF(E7="","",E7-F7-G7) | I7: =IF(OR(B7="",B7=0),"",D7/B7)
F8: =IF(E8="","",E8*$L$4+D8*$L$5) | H8: =IF(E8="","",E8-F8-G8) | I8: =IF(OR(B8="",B8=0),"",D8/B8)
F9: =IF(E9="","",E9*$L$4+D9*$L$5) | H9: =IF(E9="","",E9-F9-G9) | I9: =IF(OR(B9="",B9=0),"",D9/B9)
F10: =IF(E10="","",E10*$L$4+D10*$L$5) | H10: =IF(E10="","",E10-F10-G10) | I10: =IF(OR(B10="",B10=0),"",D10/B10)
F11: =IF(E11="","",E11*$L$4+D11*$L$5) | H11: =IF(E11="","",E11-F11-G11) | I11: =IF(OR(B11="",B11=0),"",D11/B11)
F12: =IF(E12="","",E12*$L$4+D12*$L$5) | H12: =IF(E12="","",E12-F12-G12) | I12: =IF(OR(B12="",B12=0),"",D12/B12)
F13: =IF(E13="","",E13*$L$4+D13*$L$5) | H13: =IF(E13="","",E13-F13-G13) | I13: =IF(OR(B13="",B13=0),"",D13/B13)
F14: =IF(E14="","",E14*$L$4+D14*$L$5) | H14: =IF(E14="","",E14-F14-G14) | I14: =IF(OR(B14="",B14=0),"",D14/B14)
F15: =IF(E15="","",E15*$L$4+D15*$L$5) | H15: =IF(E15="","",E15-F15-G15) | I15: =IF(OR(B15="",B15=0),"",D15/B15)
F16: =IF(E16="","",E16*$L$4+D16*$L$5) | H16: =IF(E16="","",E16-F16-G16) | I16: =IF(OR(B16="",B16=0),"",D16/B16)
F17: =IF(E17="","",E17*$L$4+D17*$L$5) | H17: =IF(E17="","",E17-F17-G17) | I17: =IF(OR(B17="",B17=0),"",D17/B17)
... F56: =IF(E56="","",E56*$L$4+D56*$L$5) | H56: =IF(E56="","",E56-F56-G56) | I56: =IF(OR(B56="",B56=0),"",D56/B56)
A58: SUMME | B58: =SUM(B5:B56) -> 120 | C58: =SUM(C5:C56) -> 9 | D58: =SUM(D5:D56) -> 1 | E58: =SUM(E5:E56) -> 12 | F58: =SUM(F5:F56) -> 1.56 | G58: =SUM(G5:G56) -> 7 | H58: =SUM(H5:H56) -> 3.44 | I58: =IF(B58=0,"",D58/B58) -> 0.0083333333
